sqlite_daq/__init__.py
sqlite_daq/sqlite_daq.py
sqlite_daq-0.1.0.dist-info/licenses/LICENSE
sqlite_daq-0.1.0.dist-info/METADATA
sqlite_daq-0.1.0.dist-info/WHEEL
sqlite_daq-0.1.0.dist-info/top_level.txt
sqlite_daq-0.1.0.dist-info/RECORD
