Metadata-Version: 2.4
Name: sqlite-daq
Version: 0.1.0
Summary: A SQLite wrapper optimized for DAQ-style, append-only logging.
Author-email: jjmajor142 <jjmajor142@gmail.com>
License: MIT
Requires-Python: >=3.8
License-File: LICENSE
Requires-Dist: sqlite3
Dynamic: license-file
